[
  {
    "id": 750,
    "author": "INEMA",
    "date": "2025-02-25T01:28:44+00:00",
    "text": "O **Replicate.com** é uma plataforma que permite rodar modelos de inteligência artificial diretamente na nuvem sem precisar configurar ou manter infraestrutura própria. Ele é muito usado para **executar modelos de machine learning** de forma fácil e rápida, sem a necessidade de instalar bibliotecas ou ter um ambiente de desenvolvimento local configurado.\n\n## Como funciona?\n1. **Escolha um modelo**: O Replicate oferece uma biblioteca de modelos treinados, como **Stable Diffusion (para gerar imagens)**, **Whisper (para transcrição de áudio)**, **LLaMA e GPT (para processamento de linguagem natural)**, entre outros.\n2. **Execute na nuvem**: Você pode rodar os modelos diretamente no site ou via API sem precisar configurar GPUs ou servidores.\n3. **API acessível**: Com apenas algumas chamadas REST, é possível enviar dados e receber os resultados do modelo de IA.\n4. **Pague pelo uso**: O Replicate funciona no modelo **pay-per-use**, ou seja, você só paga pelo tempo de processamento dos modelos que usar.\n\n## Vantagens do Replicate\n- **Facilidade de uso**: Não é necessário instalar pacotes complexos nem configurar servidores.\n- **Acesso a modelos poderosos**: Permite usar modelos de ponta sem precisar treinar ou ajustar hiperparâmetros.\n- **Escalabilidade**: Como roda na nuvem, pode processar tarefas pesadas sem depender do seu hardware local.\n- **Flexibilidade**: Oferece uma API simples para integrar modelos de IA a aplicações, sites e automações.\n- **Custo sob demanda**: Você paga apenas pelo tempo de uso, sem precisar manter uma infraestrutura cara.\n\n### Para quem é indicado?\n- **Desenvolvedores e empresas** que querem integrar IA sem gerenciar infraestrutura.\n- **Pesquisadores** que desejam testar modelos rapidamente.\n- **Criadores de conteúdo e designers** que querem gerar imagens, transcrever áudios, ou usar IA de forma prática.\n\nSe você quiser testar, o site oficial é: [https://replicate.com](https://replicate.com)",
    "has_media": true,
    "media_type": "MessageMediaWebPage"
  },
  {
    "id": 701,
    "author": "Mara",
    "date": "2025-02-17T19:28:57+00:00",
    "text": "5",
    "has_media": false,
    "media_type": null
  },
  {
    "id": 17,
    "author": "INEMA",
    "date": "2024-12-25T02:04:55+00:00",
    "text": "4",
    "has_media": false,
    "media_type": null
  },
  {
    "id": 16,
    "author": "INEMA",
    "date": "2024-12-25T02:04:53+00:00",
    "text": "3",
    "has_media": false,
    "media_type": null
  },
  {
    "id": 15,
    "author": "INEMA",
    "date": "2024-12-25T02:04:51+00:00",
    "text": "3",
    "has_media": false,
    "media_type": null
  },
  {
    "id": 14,
    "author": "INEMA",
    "date": "2024-12-25T02:04:49+00:00",
    "text": "1",
    "has_media": false,
    "media_type": null
  },
  {
    "id": 13,
    "author": "INEMA",
    "date": "2024-12-25T02:04:44+00:00",
    "text": "",
    "has_media": false,
    "media_type": null
  }
]